thelper/__init__.py
thelper/__main__.py
thelper/_thelper.c
thelper/cli.py
thelper/utils.py
thelper/data/__init__.py
thelper/data/parsers.py
thelper/data/samplers.py
thelper/data/utils.py
thelper/gui/__init__.py
thelper/gui/annotators.py
thelper/gui/utils.py
thelper/nn/__init__.py
thelper/nn/coordconv.py
thelper/nn/densenet.py
thelper/nn/inceptionresnetv2.py
thelper/nn/mobilenet.py
thelper/nn/resnet.py
thelper/nn/utils.py
thelper/optim/__init__.py
thelper/optim/metrics.py
thelper/optim/schedulers.py
thelper/optim/utils.py
thelper/tasks/__init__.py
thelper/tasks/classif.py
thelper/tasks/utils.py
thelper/train/__init__.py
thelper/train/trainers.py
thelper/train/utils.py
thelper/transforms/__init__.py
thelper/transforms/operations.py
thelper/transforms/utils.py
thelper/transforms/wrappers.py
thelper-0.1.0.dist-info/AUTHORS.rst
thelper-0.1.0.dist-info/LICENSE
thelper-0.1.0.dist-info/METADATA
thelper-0.1.0.dist-info/WHEEL
thelper-0.1.0.dist-info/entry_points.txt
thelper-0.1.0.dist-info/top_level.txt
thelper-0.1.0.dist-info/RECORD
