Metadata-Version: 2.1
Name: thelper
Version: 0.1.0
Summary: Provides training help & tools for PyTorch-based machine learning projects.
Home-page: https://github.com/plstcharles/thelper
Author: Pierre-Luc St-Charles
Author-email: stcharpl@crim.ca
License: Apache Software License 2.0
Keywords: pytorch,trainer,loader
Platform: UNKNOWN
Classifier: Development Status :: 2 - Pre-Alpha
Classifier: Intended Audience :: Developers
Classifier: Intended Audience :: Science/Research
Classifier: Topic :: Scientific/Engineering :: Artificial Intelligence
Classifier: License :: OSI Approved :: Apache Software License
Classifier: Natural Language :: English
Classifier: Operating System :: Unix
Classifier: Operating System :: POSIX
Classifier: Operating System :: Microsoft :: Windows
Classifier: Programming Language :: Python :: 3
Classifier: Programming Language :: Python :: 3.6
Classifier: Programming Language :: Python :: Implementation :: CPython
Requires-Python: ~=3.5
Requires-Dist: augmentor (>=0.2.2)
Requires-Dist: matplotlib (>=2.2.2)
Requires-Dist: numpy (>=1.14.0)
Requires-Dist: opencv-python (>=3.3.0)
Requires-Dist: torch (>=0.4.0)
Requires-Dist: pynput (>=1.4)
Requires-Dist: scikit-learn (>=0.19.1)
Requires-Dist: torchvision (>=0.2.1)
Requires-Dist: tensorboardX (==1.2.0)
Provides-Extra: rst
Requires-Dist: docutils (>=0.11); extra == 'rst'
